robust_segment_anything/__init__.py
robust_segment_anything/automatic_mask_generator.py
robust_segment_anything/build_sam.py
robust_segment_anything/predictor.py
robust_segment_anything/modeling/__init__.py
robust_segment_anything/modeling/common.py
robust_segment_anything/modeling/components.py
robust_segment_anything/modeling/image_encoder.py
robust_segment_anything/modeling/mask_decoder.py
robust_segment_anything/modeling/prompt_encoder.py
robust_segment_anything/modeling/sam.py
robust_segment_anything/modeling/transformer.py
robust_segment_anything/utils/__init__.py
robust_segment_anything/utils/amg.py
robust_segment_anything/utils/onnx.py
robust_segment_anything/utils/transforms.py
robust_segment_anything-1.0.0.dist-info/LICENSE
robust_segment_anything-1.0.0.dist-info/METADATA
robust_segment_anything-1.0.0.dist-info/WHEEL
robust_segment_anything-1.0.0.dist-info/top_level.txt
robust_segment_anything-1.0.0.dist-info/RECORD
