Metadata-Version: 2.1
Name: robust_segment_anything
Version: 1.0.0
Summary: RobustSAM: Segment Anything Robustly on Degraded Images.
License: MIT License
Project-URL: repository, https://github.com/robustsam/RobustSAM
Keywords: deep-learning,pytorch,vision,object-segmentation
Classifier: Development Status :: 5 - Production/Stable
Classifier: Operating System :: OS Independent
Classifier: Intended Audience :: Science/Research
Classifier: Programming Language :: Python :: 3
Classifier: License :: OSI Approved :: BSD License
Classifier: Topic :: Scientific/Engineering :: Artificial Intelligence
Requires-Python: >=3.10
License-File: LICENSE
Requires-Dist: numpy >=1.23.5
Requires-Dist: torch >=2.0.0
Requires-Dist: torchvision >=0.15.1
